biomodels_restful_api_client/__init__.py
biomodels_restful_api_client/constants.py
biomodels_restful_api_client/services.py
biomodels_restful_api_client-0.1.3.dist-info/METADATA
biomodels_restful_api_client-0.1.3.dist-info/WHEEL
biomodels_restful_api_client-0.1.3.dist-info/licenses/LICENSE
biomodels_restful_api_client-0.1.3.dist-info/RECORD
