Metadata-Version: 2.3
Name: biomodels_restful_api_client
Version: 0.1.3
Summary: BioModels RESTful API - Web Services
Project-URL: Homepage, https://github.com/EBI-BioModels/biomodels-resftful-api-client
Project-URL: Bug Tracker, https://github.com/EBI-BioModels/biomodels-resftful-api-client/issues
Author-email: Tung Nguyen <tnguyen@ebi.ac.uk>, Tung Nguyen <nvntung@gmail.com>
Classifier: License :: OSI Approved :: MIT License
Classifier: Operating System :: OS Independent
Classifier: Programming Language :: Python :: 3
Requires-Python: >=3.7
